{
  "name": "The Witch",
  "type": "playbook",
  "img": "icons/svg/book.svg",
  "system": {
    "description": "<div class=\"playbook\">\n<section>\n<div class=\"playbook-header\">\n<h1>Witch</h1>\n<p>Destiny Playbook</p>\n</div>\n<p><em>When you can conjure hammers at will, every problem starts looking like an eldritch nail.</em></p>\n</section>\n<section class=\"rules\">\n<div>\n<h2>Requirements</h2>\n<p><strong>To become the Witch,</strong> you must have solved at least three problems using Magic when they could have been solved otherwise.</p>\n<p>The Witch starts with a Witch Custom Move of their choice.</p>\n<h2>Advancement</h2>\n<p><strong>When you Level Up,</strong> choose one Advancement from either this list or from your Basic Playbook, then mark it. You may only choose each option once.</p>\n<ul>\n<li>Increase one of your stats by +1, to a maximum of +3.</li>\n<li>Take a Witch Custom.</li>\n<li>Take a Witch Custom.</li>\n<li>Take a Witch Custom.</li>\n<li>Take a Witch Custom.</li>\n</ul>\n</div>\n<div>\n<h2>Custom Moves</h2>\n<p>@UUID[Compendium.fellowship-pbta.the-witch.Item.c00fmfDXa4Ka6VmU]{Conjurer}</p>\n<p>@UUID[Compendium.fellowship-pbta.the-witch.Item.lM9oC01vz3IkNOcl]{Defying gravity}</p>\n<p>@UUID[Compendium.fellowship-pbta.the-witch.Item.zErZ9a5se0CkoZJL]{Potion's master}</p>\n<p>@UUID[Compendium.fellowship-pbta.the-witch.Item.709UjlIYYIvQzsKX]{Stitched together}</p>\n<p>@UUID[Compendium.fellowship-pbta.the-witch.Item.EiBzXf5Je3BeB06p]{Turn you into a newt}</p>\n<p>@UUID[Compendium.fellowship-pbta.the-witch.Item.POE8Pf3EmUEoUv2d]{Witch's familiar}</p>\n</div>\n</section>\n</div>",
    "slug": "the-witch",
    "actorType": "destiny"
  },
  "effects": [],
  "folder": null,
  "flags": {
    "core": {}
  },
  "_stats": {
    "systemId": "pbta",
    "systemVersion": "0.9.4",
    "coreVersion": "11.315",
    "createdTime": 1712986447876,
    "modifiedTime": 1713681614701,
    "lastModifiedBy": "ghfbDt2b5Xd0vUiQ"
  },
  "_id": "pRASKbOFcdswLRjX",
  "sort": 0,
  "ownership": {
    "default": 0,
    "ZNFwJXLh8ZaZBK1b": 3
  },
  "_key": "!items!pRASKbOFcdswLRjX"
}
