{
  "folder": "RLFVF44OeSsj7AF3",
  "name": "We need your help! (sense)",
  "type": "move",
  "_id": "oA58Cxm8OxoGEeXJ",
  "img": "icons/svg/aura.svg",
  "system": {
    "description": "<div class=\"page\" title=\"Page 1\">\n<div class=\"layoutArea\">\n<div class=\"column\">\n<p><strong>When you go to find help</strong>, the Overlord will tell you who you find. <strong>If you ask for their aid,</strong> roll +Sense.</p>\n</div>\n</div>\n</div>",
    "moveType": "destiny",
    "rollFormula": "",
    "moveResults": {
      "failure": {
        "key": "system.moveResults.failure.value",
        "label": "Complications...",
        "value": "<div class=\"page\" title=\"Page 1\">\n<div class=\"layoutArea\">\n<div class=\"column\">\n<p>they will not help you, and they may even mean you harm.</p>\n</div>\n</div>\n</div>"
      },
      "partial": {
        "key": "system.moveResults.partial.value",
        "label": "Partial success.",
        "value": "<div class=\"page\" title=\"Page 1\">\n<div class=\"layoutArea\">\n<div class=\"column\">\n<p>choose two, or pay a price to take three. Regardless of your choices, they will help you, and they are sufficient to help with your need.</p>\n</div>\n</div>\n</div>\n<ul>\n<li>They will help immediately, dropping whatever they were doing</li>\n<li>They ask no questions and need no explanation.</li>\n<li>They demand no favors or payment.</li>\n<li>You Forge A Bond with them.</li>\n</ul>"
      },
      "success": {
        "key": "system.moveResults.success.value",
        "label": "Success!",
        "value": "<div class=\"page\" title=\"Page 1\">\n<div class=\"layoutArea\">\n<div class=\"column\">\n<p>All four</p>\n<ul>\n<li>They will help immediately, dropping whatever they were doing</li>\n<li>They ask no questions and need no explanation.</li>\n<li>They demand no favors or payment.</li>\n<li>You Forge A Bond with them.</li>\n</ul>\n</div>\n</div>\n</div>"
      }
    },
    "uses": 0,
    "playbook": "",
    "rollType": "sense",
    "rollMod": 0,
    "actorType": "destiny",
    "choices": ""
  },
  "effects": [],
  "sort": 0,
  "ownership": {
    "default": 0,
    "ghfbDt2b5Xd0vUiQ": 3
  },
  "flags": {},
  "_stats": {
    "systemId": "pbta",
    "systemVersion": "0.9.4",
    "coreVersion": "11.315",
    "createdTime": 1713340293962,
    "modifiedTime": 1713340862416,
    "lastModifiedBy": "ghfbDt2b5Xd0vUiQ"
  },
  "_key": "!items!oA58Cxm8OxoGEeXJ"
}
