{
  "folder": "PbvEWyNCw9rg6pRH",
  "name": "GROUP OF KOBOLD POKERS",
  "type": "fellowship-pbta.companion",
  "_id": "mMVsSyYXnwr6sSxV",
  "img": "icons/svg/item-bag.svg",
  "system": {
    "typeName": "GROUP OF KOBOLD POKERS",
    "typeDescription": "These kobolds form a phalanx, each shield protecting the warrior next to them. As a Group, each of their stats can be damaged twice.",
    "inDespair": false,
    "stats": [
      {
        "name": "use the pointy bit",
        "damaged": false
      },
      {
        "name": "big shield",
        "damaged": false
      }
    ]
  },
  "effects": [],
  "sort": 0,
  "ownership": {
    "default": 0
  },
  "flags": {},
  "_stats": {
    "compendiumSource": null,
    "duplicateSource": null,
    "coreVersion": "13.346",
    "systemId": "pbta",
    "systemVersion": "1.1.12",
    "createdTime": null,
    "modifiedTime": null,
    "lastModifiedBy": null,
    "exportSource": null
  },
  "_key": "!items!mMVsSyYXnwr6sSxV"
}
