{
  "name": "Blade of Darkest Night",
  "type": "move",
  "_id": "PFNzxnXK8xrammgp",
  "img": "icons/svg/aura.svg",
  "system": {
    "description": "<p>One of you is given a powerful, cursed weapon. It has the tags <em>Melee</em> and <em>Necrotic</em>. The player who is taking it describes what it looks like. It whispers dark and terrible secrets to whoever holds it, giving them insight into the world, but also driving them slowly mad.</p><p>The holder of this weapon can <em>Command Lore</em> about dark and terrible things, and gains the Agenda <strong>Always Dig Deeper</strong>: You need to know every secret and find every treasure, and you despise secrets and secret-keepers.</p>",
    "moveType": "fellowship",
    "rollFormula": "",
    "moveResults": {
      "failure": {
        "key": "system.moveResults.failure.value",
        "label": "Complications...",
        "value": ""
      },
      "partial": {
        "key": "system.moveResults.partial.value",
        "label": "Partial success.",
        "value": ""
      },
      "success": {
        "key": "system.moveResults.success.value",
        "label": "Success!",
        "value": ""
      }
    },
    "uses": 0,
    "rollType": "",
    "rollMod": 0,
    "actorType": "character",
    "choices": ""
  },
  "effects": [],
  "folder": null,
  "sort": 0,
  "ownership": {
    "default": 0,
    "JSvWyw8NYcFGMf4t": 3
  },
  "flags": {},
  "_stats": {
    "compendiumSource": null,
    "duplicateSource": null,
    "exportSource": null,
    "coreVersion": "13.346",
    "systemId": "pbta",
    "systemVersion": "1.1.21",
    "createdTime": 1753053033384,
    "modifiedTime": 1753053273609,
    "lastModifiedBy": "JSvWyw8NYcFGMf4t"
  },
  "_key": "!items!PFNzxnXK8xrammgp"
}
