{
  "name": "Our Forge is Your Forge",
  "type": "move",
  "_id": "Z3AJWCQQe4zQzRuZ",
  "img": "modules/fellowship-pbta/assets/icons/round-table.svg",
  "system": {
    "description": "<p>The dwarves here will replace or re-forge as many of your weapons and vehicles as you like. All such items in any players' Gear gain the <strong>Dwarf-Made</strong> tag, making them effectively indestructible.</p>",
    "moveType": "fellowship",
    "rollFormula": "",
    "moveResults": {
      "failure": {
        "key": "system.moveResults.failure.value",
        "label": "Complications...",
        "value": ""
      },
      "partial": {
        "key": "system.moveResults.partial.value",
        "label": "Partial success.",
        "value": ""
      },
      "success": {
        "key": "system.moveResults.success.value",
        "label": "Success!",
        "value": ""
      }
    },
    "uses": 0,
    "rollType": "",
    "rollMod": 0,
    "actorType": "character",
    "choices": ""
  },
  "effects": [],
  "folder": null,
  "sort": 0,
  "ownership": {
    "default": 0,
    "JSvWyw8NYcFGMf4t": 3
  },
  "flags": {},
  "_stats": {
    "compendiumSource": null,
    "duplicateSource": null,
    "exportSource": null,
    "coreVersion": "13.346",
    "systemId": "pbta",
    "systemVersion": "1.1.21",
    "createdTime": 1753043049839,
    "modifiedTime": 1753052870615,
    "lastModifiedBy": "JSvWyw8NYcFGMf4t"
  },
  "_key": "!items!Z3AJWCQQe4zQzRuZ"
}
