{
  "folder": "cMN48Wsh8FCRjrOg",
  "name": "Fine axe",
  "type": "equipment",
  "_id": "vs4SzrOCPKpLOYCf",
  "img": "icons/svg/item-bag.svg",
  "system": {
    "description": "<div class=\"page\" title=\"Page 7\">\n<div class=\"layoutArea\">\n<div class=\"column\">\n<p>gilded and engraved</p>\n</div>\n</div>\n</div>",
    "uses": 0,
    "playbook": "The Dwarf",
    "quantity": 1,
    "weight": 0,
    "tags": "",
    "itemType": "",
    "equipmentType": "gear",
    "actorType": "dwarf"
  },
  "effects": [],
  "sort": 0,
  "ownership": {
    "default": 0,
    "ZNFwJXLh8ZaZBK1b": 3
  },
  "flags": {},
  "_stats": {
    "systemId": "pbta",
    "systemVersion": "0.9.4",
    "coreVersion": "11.315",
    "createdTime": 1713059121389,
    "modifiedTime": 1713071341069,
    "lastModifiedBy": "ZNFwJXLh8ZaZBK1b"
  },
  "_key": "!items!vs4SzrOCPKpLOYCf"
}
