{
  "folder": "6e4XYCaGFWFDhJYa",
  "name": "DARING DEVILS",
  "type": "move",
  "_id": "laOl6iIzwJ82ZIme",
  "img": "icons/svg/aura.svg",
  "system": {
    "description": "<p>When you need a cool prop appropriate to your environment, like a chandelier to drop, a window to leap out of, or a vine to swing from, it's there.</p><p>When you use the terrain to protect you, you may <em>Overcome</em> using +Grace instead of +Blood. Leaping off of tall places to escape danger always counts.</p>",
    "moveType": "core",
    "rollFormula": "",
    "moveResults": {
      "failure": {
        "key": "system.moveResults.failure.value",
        "label": "Complications...",
        "value": ""
      },
      "partial": {
        "key": "system.moveResults.partial.value",
        "label": "Partial success.",
        "value": ""
      },
      "success": {
        "key": "system.moveResults.success.value",
        "label": "Success!",
        "value": ""
      }
    },
    "uses": 0,
    "rollType": "",
    "rollMod": 0,
    "actorType": "character",
    "choices": ""
  },
  "effects": [],
  "sort": 0,
  "ownership": {
    "default": 0
  },
  "flags": {},
  "_stats": {
    "compendiumSource": null,
    "duplicateSource": null,
    "coreVersion": "13.346",
    "systemId": "pbta",
    "systemVersion": "1.1.12",
    "createdTime": null,
    "modifiedTime": null,
    "lastModifiedBy": null,
    "exportSource": null
  },
  "_key": "!items!laOl6iIzwJ82ZIme"
}
