{
  "folder": "mV3Ea48DGE0PAcuH",
  "name": "Halfling pipeleaf",
  "type": "equipment",
  "_id": "yuhPQxjUmQdF9uQ8",
  "img": "icons/svg/item-bag.svg",
  "system": {
    "description": "<div class=\"page\" title=\"Page 15\">\n<div class=\"layoutArea\">\n<div class=\"column\">\n<p>Halfling pipeleaf is a particularly popular kind of tobacco, especially among wizards. <strong>When you share your pipeleaf with another</strong> <strong>(1 Use)</strong>, @UUID[Compendium.fellowship-pbta.basic-moves.Item.gjr4zxZDb4fnI9bo]{Speak Softly} with them as if you rolled a 7-9.</p>\n</div>\n</div>\n</div>",
    "uses": 2,
    "playbook": "The Halfling",
    "quantity": 1,
    "weight": 0,
    "tags": "[{\"value\":\"Slow\"},{\"value\":\"Drunk\"}]",
    "itemType": "",
    "equipmentType": "gear",
    "actorType": "character"
  },
  "effects": [],
  "sort": 0,
  "ownership": {
    "default": 0,
    "ZNFwJXLh8ZaZBK1b": 3
  },
  "flags": {},
  "_stats": {
    "systemId": "pbta",
    "systemVersion": "0.9.4",
    "coreVersion": "11.315",
    "createdTime": 1713073816867,
    "modifiedTime": 1713074182442,
    "lastModifiedBy": "ZNFwJXLh8ZaZBK1b"
  },
  "_key": "!items!yuhPQxjUmQdF9uQ8"
}
